psc_datalogger/__init__.py
psc_datalogger/__main__.py
psc_datalogger/_version.py
psc_datalogger/connection.py
psc_datalogger/gui.py
psc_datalogger/multimeter.py
psc_datalogger/statusbar.py
psc_datalogger/testprog.py
psc_datalogger/temperature/__init__.py
psc_datalogger/temperature/converter.py
psc_datalogger-1.1.0.dist-info/LICENSE
psc_datalogger-1.1.0.dist-info/METADATA
psc_datalogger-1.1.0.dist-info/WHEEL
psc_datalogger-1.1.0.dist-info/entry_points.txt
psc_datalogger-1.1.0.dist-info/top_level.txt
psc_datalogger-1.1.0.dist-info/RECORD
