Metadata-Version: 2.1
Name: psc-datalogger
Version: 1.1.0
Summary: Logs data from one-or-more devices for an extended period of time
Author-email: Alex Wells <alex.wells@diamond.ac.uk>
License:                                  Apache License
Project-URL: GitHub, https://github.com/DiamondLightSource/psc-datalogger
Classifier: Development Status :: 3 - Alpha
Classifier: License :: OSI Approved :: Apache Software License
Classifier: Programming Language :: Python :: 3.7
Classifier: Programming Language :: Python :: 3.8
Classifier: Programming Language :: Python :: 3.9
Classifier: Programming Language :: Python :: 3.10
Classifier: Programming Language :: Python :: 3.11
Requires-Python: >=3.7
License-File: LICENSE
Requires-Dist: qasync
Requires-Dist: PyQt5
Requires-Dist: pyserial
Requires-Dist: pyvisa
Requires-Dist: pyvisa-py
Requires-Dist: psutil
Requires-Dist: zeroconf
Provides-Extra: dev
Requires-Dist: copier; extra == "dev"
Requires-Dist: pipdeptree; extra == "dev"
Requires-Dist: pre-commit; extra == "dev"
Requires-Dist: pyinstaller; extra == "dev"
Requires-Dist: pyright; extra == "dev"
Requires-Dist: pytest; extra == "dev"
Requires-Dist: pytest-cov; extra == "dev"
Requires-Dist: pytest-qt; extra == "dev"
Requires-Dist: ruff; extra == "dev"
Requires-Dist: tox-direct; extra == "dev"
Requires-Dist: types-mock; extra == "dev"
